pypolate/__init__.py
pypolate/areal.py
pypolate/binary.py
pypolate/expert.py
pypolate/lim_var.py
pypolate/n_class.py
pypolate/parcel.py
pypolate/pypolate.py
pypolate-0.0.5.dist-info/LICENSE.txt
pypolate-0.0.5.dist-info/METADATA
pypolate-0.0.5.dist-info/WHEEL
pypolate-0.0.5.dist-info/top_level.txt
pypolate-0.0.5.dist-info/RECORD
