Metadata-Version: 2.1
Name: pypolate
Version: 0.0.5
Summary: A package for performing spatial interpolation with vector data
Home-page: https://github.com/mikeRobWard/PyPolate
Author: Michael Ward & John Fitzgibbons
Author-email: michaelward94@gmail.com
License: GPLv3+
Keywords: spatial interpolation
Platform: UNKNOWN
Classifier: Development Status :: 5 - Production/Stable
Classifier: Intended Audience :: Science/Research
Classifier: License :: OSI Approved :: GNU General Public License v3 or later (GPLv3+)
Classifier: Programming Language :: Python :: 3
Classifier: Topic :: Scientific/Engineering :: GIS
Requires-Python: >=3.7
License-File: LICENSE.txt
Requires-Dist: geopandas
Requires-Dist: pandas
